Workbook

Sheet Read Me
A1: KudiTrack AI: ClubKonnect price list
A2: Snapshot taken 25 Sep 2026, 21:43 WAT
A4: Source | B4: Live from ClubKonnect via KudiTrack's clubkonnect edge function (GitHub Actions run 36193015699). Data-plan costs come from ClubKonnect's APIDatabundlePlansV2; airtime and print-airtime discounts from APIAirtimeDiscountV1 / APIEPINDiscountV2, all read with KudiTrack's own ClubKonnect account.
A5: What 'ClubKonnect cost' means | B5: What ClubKonnect charges your wallet for one unit. Your profit on a sale is your sale price minus this cost.
A6: How to use | B6: Type your price in the YELLOW column on each sheet. Profit, margin and a LOSS warning update automatically. Leave a yellow cell blank if you have not decided yet.
A7: Example row | B7: Row 5 of 'Data Plans' (MTN 500 MB weekly SME) has an example sale price of ₦350 filled in so you can see the format. Change or delete it.
A8: Suggested price | B8: Each sheet has a 'Suggested price' column = cost × (1 + markup). Set the markup on the 'Settings' sheet. It is capped at the network's own price (face value for airtime PINs), since customers won't pay more than that.
A9: Current KudiTrack price | B9: Data: what the app shows today (from src/data/billPrices.js). Print airtime: cost + the Enterprise fee on 'Settings' (the app rounds up to the next naira). Blank means the app has no fixed price for that plan.
A10: Print Data | B10: The app loads print-data plans from the same ClubKonnect plan list as direct data and charges the same unit price, so the cost column is the same list. Confirm data-PIN pricing on your ClubKonnect dashboard if in doubt.
A11: Network price | B11: For Awoof and Direct plans, ClubKonnect's plan ID carries the network's official price (e.g. 800.01 = ₦800). SME plan IDs are sizes, so this is blank for SME.
A12: Refreshing | B12: Prices change. Re-run the 'ClubKonnect price snapshot' GitHub Action (.github/workflows/ck-price-snapshot.yml) and ask for the sheet to be rebuilt.
A13: Colour key | B13: Yellow fill = you type here · Blue text = numbers taken from ClubKonnect · Black = formulas · Green text = linked from the Settings sheet · Red 'LOSS' = your price is below cost.

Sheet Summary
A1: Summary by network
A2: Counts and averages update as you fill in sale prices
A4: Network | B4: Data plans | C4: Cheapest data cost (₦) | D4: Priced by you | E4: Selling at a loss | F4: Avg data margin | G4: Print airtime priced | H4: Avg print airtime margin
A5: MTN | B5: =COUNTIF('Data Plans'!$A$5:$A$140,A5) -> 37 | C5: =_xlfn.MINIFS('Data Plans'!$G$5:$G$140,'Data Plans'!$A$5:$A$140,A5) -> 94.09 | D5: =COUNTIFS('Data Plans'!$A$5:$A$140,A5,'Data Plans'!$I$5:$I$140,"<>") -> 1 | E5: =COUNTIFS('Data Plans'!$A$5:$A$140,A5,'Data Plans'!$L$5:$L$140,"LOSS") -> 0 | F5: =IFERROR(AVERAGEIFS('Data Plans'!$K$5:$K$140,'Data Plans'!$A$5:$A$140,A5,'Data Plans'!$I$5:$I$140,"<>"),"") -> 0.15142857 | G5: =COUNTIFS('Airtime Print'!$A$5:$A$24,A5,'Airtime Print'!$F$5:$F$24,"<>") -> 0 | H5: =IFERROR(AVERAGEIFS('Airtime Print'!$H$5:$H$24,'Airtime Print'!$A$5:$A$24,A5,'Airtime Print'!$F$5:$F$24,"<>"),"")
A6: Glo | B6: =COUNTIF('Data Plans'!$A$5:$A$140,A6) -> 41 | C6: =_xlfn.MINIFS('Data Plans'!$G$5:$G$140,'Data Plans'!$A$5:$A$140,A6) -> 92.64 | D6: =COUNTIFS('Data Plans'!$A$5:$A$140,A6,'Data Plans'!$I$5:$I$140,"<>") -> 0 | E6: =COUNTIFS('Data Plans'!$A$5:$A$140,A6,'Data Plans'!$L$5:$L$140,"LOSS") -> 0 | F6: =IFERROR(AVERAGEIFS('Data Plans'!$K$5:$K$140,'Data Plans'!$A$5:$A$140,A6,'Data Plans'!$I$5:$I$140,"<>"),"") | G6: =COUNTIFS('Airtime Print'!$A$5:$A$24,A6,'Airtime Print'!$F$5:$F$24,"<>") -> 0 | H6: =IFERROR(AVERAGEIFS('Airtime Print'!$H$5:$H$24,'Airtime Print'!$A$5:$A$24,A6,'Airtime Print'!$F$5:$F$24,"<>"),"")
A7: Airtel | B7: =COUNTIF('Data Plans'!$A$5:$A$140,A7) -> 27 | C7: =_xlfn.MINIFS('Data Plans'!$G$5:$G$140,'Data Plans'!$A$5:$A$140,A7) -> 470.37 | D7: =COUNTIFS('Data Plans'!$A$5:$A$140,A7,'Data Plans'!$I$5:$I$140,"<>") -> 0 | E7: =COUNTIFS('Data Plans'!$A$5:$A$140,A7,'Data Plans'!$L$5:$L$140,"LOSS") -> 0 | F7: =IFERROR(AVERAGEIFS('Data Plans'!$K$5:$K$140,'Data Plans'!$A$5:$A$140,A7,'Data Plans'!$I$5:$I$140,"<>"),"") | G7: =COUNTIFS('Airtime Print'!$A$5:$A$24,A7,'Airtime Print'!$F$5:$F$24,"<>") -> 0 | H7: =IFERROR(AVERAGEIFS('Airtime Print'!$H$5:$H$24,'Airtime Print'!$A$5:$A$24,A7,'Airtime Print'!$F$5:$F$24,"<>"),"")
A8: 9mobile | B8: =COUNTIF('Data Plans'!$A$5:$A$140,A8) -> 31 | C8: =_xlfn.MINIFS('Data Plans'!$G$5:$G$140,'Data Plans'!$A$5:$A$140,A8) -> 25 | D8: =COUNTIFS('Data Plans'!$A$5:$A$140,A8,'Data Plans'!$I$5:$I$140,"<>") -> 0 | E8: =COUNTIFS('Data Plans'!$A$5:$A$140,A8,'Data Plans'!$L$5:$L$140,"LOSS") -> 0 | F8: =IFERROR(AVERAGEIFS('Data Plans'!$K$5:$K$140,'Data Plans'!$A$5:$A$140,A8,'Data Plans'!$I$5:$I$140,"<>"),"") | G8: =COUNTIFS('Airtime Print'!$A$5:$A$24,A8,'Airtime Print'!$F$5:$F$24,"<>") -> 0 | H8: =IFERROR(AVERAGEIFS('Airtime Print'!$H$5:$H$24,'Airtime Print'!$A$5:$A$24,A8,'Airtime Print'!$F$5:$F$24,"<>"),"")
A9: Total | B9: =SUM(B5:B8) -> 136 | D9: =SUM(D5:D8) -> 1 | E9: =SUM(E5:E8) -> 0 | G9: =SUM(G5:G8) -> 0

Sheet Settings
A1: Settings and ClubKonnect discounts
A2: Discounts read live 25 Sep 2026, 21:43 WAT
A4: Markup for 'Suggested price' | B4: 0.05 | C4: Your choice. 5% is a starting point.
A5: Enterprise bill fee (print airtime) | B5: 0.01 | C5: Default of platform_config.enterprise_bill_fee_pct (0.01). Change it if you set a different value in the admin portal.
A8: Network | B8: Airtime (VTU) discount | C8: Print airtime (EPIN) discount | D8: VTU min (₦) | E8: VTU max (₦) | F8: Cost of ₦1,000 airtime (VTU)
A9: MTN | B9: 0.03 | C9: 0.01 | D9: 50 | E9: 200000 | F9: =1000*(1-B9) -> 970
A10: Glo | B10: 0.08 | C10: 0.02 | D10: 50 | E10: 200000 | F10: =1000*(1-B10) -> 920
A11: Airtel | B11: 0.03 | C11: 0.02 | D11: 50 | E11: 200000 | F11: =1000*(1-B11) -> 970
A12: 9mobile | B12: 0.07 | C12: 0.05 | D12: 50 | E12: 200000 | F12: =1000*(1-B12) -> 930
A14: Source: ClubKonnect APIAirtimeDiscountV1 and APIEPINDiscountV2, read 25 Sep 2026, 21:43 WAT.

Sheet Data Plans
A1: Data plans: ClubKonnect cost and your sale price
A2: 136 plans across 4 networks · 25 Sep 2026, 21:43 WAT
A4: Network | B4: Type | C4: Plan | D4: Validity | E4: CK plan ID | F4: Network price (₦) | G4: ClubKonnect cost (₦) | H4: Current KudiTrack price (₦) | I4: YOUR SALE PRICE (₦) | J4: Profit per sale (₦) | K4: Margin | L4: Status | M4: Suggested price (₦) | N4: CK discount vs network price
A5: MTN | B5: SME | C5: 500 MB - Weekly | D5: 7 days | E5: 500 | G5: 297 | H5: 400 | I5: 350 | J5: =IF(I5="","",I5-G5) -> 53 | K5: =IF(OR(I5="",I5=0),"",J5/I5) -> 0.15142857 | L5: =IF(I5="","Set price",IF(I5<G5,"LOSS",IF(I5=G5,"Break-even","OK"))) -> OK | M5: =IF(F5="",CEILING(G5*(1+Settings!$B$4),5),MIN(F5,CEILING(G5*(1+Settings!$B$4),5))) -> 315 | N5: =IF(F5="","",1-G5/F5)
A6: MTN | B6: SME | C6: 500 MB - Monthly | D6: 30 days | E6: 500.00 | G6: 307 | H6: 500 | J6: =IF(I6="","",I6-G6) | K6: =IF(OR(I6="",I6=0),"",J6/I6) | L6: =IF(I6="","Set price",IF(I6<G6,"LOSS",IF(I6=G6,"Break-even","OK"))) -> Set price | M6: =IF(F6="",CEILING(G6*(1+Settings!$B$4),5),MIN(F6,CEILING(G6*(1+Settings!$B$4),5))) -> 325 | N6: =IF(F6="","",1-G6/F6)
A7: MTN | B7: SME | C7: 1 GB - Weekly | D7: 7 days | E7: 1000 | G7: 410 | H7: 500 | J7: =IF(I7="","",I7-G7) | K7: =IF(OR(I7="",I7=0),"",J7/I7) | L7: =IF(I7="","Set price",IF(I7<G7,"LOSS",IF(I7=G7,"Break-even","OK"))) -> Set price | M7: =IF(F7="",CEILING(G7*(1+Settings!$B$4),5),MIN(F7,CEILING(G7*(1+Settings!$B$4),5))) -> 435 | N7: =IF(F7="","",1-G7/F7)
A8: MTN | B8: SME | C8: 1 GB - Monthly | D8: 30 days | E8: 1000.00 | G8: 563 | H8: 700 | J8: =IF(I8="","",I8-G8) | K8: =IF(OR(I8="",I8=0),"",J8/I8) | L8: =IF(I8="","Set price",IF(I8<G8,"LOSS",IF(I8=G8,"Break-even","OK"))) -> Set price | M8: =IF(F8="",CEILING(G8*(1+Settings!$B$4),5),MIN(F8,CEILING(G8*(1+Settings!$B$4),5))) -> 595 | N8: =IF(F8="","",1-G8/F8)
A9: MTN | B9: SME | C9: 2 GB - Weekly | D9: 7 days | E9: 2000 | G9: 820 | H9: 1200 | J9: =IF(I9="","",I9-G9) | K9: =IF(OR(I9="",I9=0),"",J9/I9) | L9: =IF(I9="","Set price",IF(I9<G9,"LOSS",IF(I9=G9,"Break-even","OK"))) -> Set price | M9: =IF(F9="",CEILING(G9*(1+Settings!$B$4),5),MIN(F9,CEILING(G9*(1+Settings!$B$4),5))) -> 865 | N9: =IF(F9="","",1-G9/F9)
A10: MTN | B10: SME | C10: 2 GB - Monthly | D10: 30 days | E10: 2000.00 | G10: 1117 | H10: 1500 | J10: =IF(I10="","",I10-G10) | K10: =IF(OR(I10="",I10=0),"",J10/I10) | L10: =IF(I10="","Set price",IF(I10<G10,"LOSS",IF(I10=G10,"Break-even","OK"))) -> Set price | M10: =IF(F10="",CEILING(G10*(1+Settings!$B$4),5),MIN(F10,CEILING(G10*(1+Settings!$B$4),5))) -> 1175 | N10: =IF(F10="","",1-G10/F10)
A11: MTN | B11: SME | C11: 3 GB - Weekly | D11: 7 days | E11: 3000 | G11: 1230 | H11: 1400 | J11: =IF(I11="","",I11-G11) | K11: =IF(OR(I11="",I11=0),"",J11/I11) | L11: =IF(I11="","Set price",IF(I11<G11,"LOSS",IF(I11=G11,"Break-even","OK"))) -> Set price | M11: =IF(F11="",CEILING(G11*(1+Settings!$B$4),5),MIN(F11,CEILING(G11*(1+Settings!$B$4),5))) -> 1295 | N11: =IF(F11="","",1-G11/F11)
A12: MTN | B12: SME | C12: 3 GB - Monthly | D12: 30 days | E12: 3000.00 | G12: 1629 | H12: 1800 | J12: =IF(I12="","",I12-G12) | K12: =IF(OR(I12="",I12=0),"",J12/I12) | L12: =IF(I12="","Set price",IF(I12<G12,"LOSS",IF(I12=G12,"Break-even","OK"))) -> Set price | M12: =IF(F12="",CEILING(G12*(1+Settings!$B$4),5),MIN(F12,CEILING(G12*(1+Settings!$B$4),5))) -> 1715 | N12: =IF(F12="","",1-G12/F12)
A13: MTN | B13: SME | C13: 5 GB - Monthly | D13: 30 days | E13: 5000.00 | G13: 2511 | H13: 2850 | J13: =IF(I13="","",I13-G13) | K13: =IF(OR(I13="",I13=0),"",J13/I13) | L13: =IF(I13="","Set price",IF(I13<G13,"LOSS",IF(I13=G13,"Break-even","OK"))) -> Set price | M13: =IF(F13="",CEILING(G13*(1+Settings!$B$4),5),MIN(F13,CEILING(G13*(1+Settings!$B$4),5))) -> 2640 | N13: =IF(F13="","",1-G13/F13)
A14: MTN | B14: Awoof | C14: 110MB Daily Plan - 1 day | D14: 1 day | E14: 100.01 | F14: 100 | G14: 94.09 | H14: 150 | J14: =IF(I14="","",I14-G14) | K14: =IF(OR(I14="",I14=0),"",J14/I14) | L14: =IF(I14="","Set price",IF(I14<G14,"LOSS",IF(I14=G14,"Break-even","OK"))) -> Set price | M14: =IF(F14="",CEILING(G14*(1+Settings!$B$4),5),MIN(F14,CEILING(G14*(1+Settings!$B$4),5))) -> 100 | N14: =IF(F14="","",1-G14/F14) -> 0.0591
A15: MTN | B15: Awoof | C15: 230MB Daily Plan - 1 day | D15: 1 day | E15: 200.01 | F15: 200 | G15: 188.18 | H15: 250 | J15: =IF(I15="","",I15-G15) | K15: =IF(OR(I15="",I15=0),"",J15/I15) | L15: =IF(I15="","Set price",IF(I15<G15,"LOSS",IF(I15=G15,"Break-even","OK"))) -> Set price | M15: =IF(F15="",CEILING(G15*(1+Settings!$B$4),5),MIN(F15,CEILING(G15*(1+Settings!$B$4),5))) -> 200 | N15: =IF(F15="","",1-G15/F15) -> 0.0591
A16: MTN | B16: Awoof | C16: 500MB Daily Plan - 1 day | D16: 1 day | E16: 350.01 | F16: 350 | G16: 329.32 | H16: 400 | J16: =IF(I16="","",I16-G16) | K16: =IF(OR(I16="",I16=0),"",J16/I16) | L16: =IF(I16="","Set price",IF(I16<G16,"LOSS",IF(I16=G16,"Break-even","OK"))) -> Set price | M16: =IF(F16="",CEILING(G16*(1+Settings!$B$4),5),MIN(F16,CEILING(G16*(1+Settings!$B$4),5))) -> 350 | N16: =IF(F16="","",1-G16/F16) -> 0.059085714
A17: MTN | B17: Awoof | C17: 1GB Daily Plan + 1.5mins. - 1 day | D17: 1 day | E17: 500.01 | F17: 500 | G17: 470.45 | H17: 500 | J17: =IF(I17="","",I17-G17) | K17: =IF(OR(I17="",I17=0),"",J17/I17) | L17: =IF(I17="","Set price",IF(I17<G17,"LOSS",IF(I17=G17,"Break-even","OK"))) -> Set price | M17: =IF(F17="",CEILING(G17*(1+Settings!$B$4),5),MIN(F17,CEILING(G17*(1+Settings!$B$4),5))) -> 495 | N17: =IF(F17="","",1-G17/F17) -> 0.0591
A18: MTN | B18: Awoof | C18: 2.5GB Daily Plan - 1 day | D18: 1 day | E18: 750.01 | F18: 750 | G18: 705.68 | H18: 750 | J18: =IF(I18="","",I18-G18) | K18: =IF(OR(I18="",I18=0),"",J18/I18) | L18: =IF(I18="","Set price",IF(I18<G18,"LOSS",IF(I18=G18,"Break-even","OK"))) -> Set price | M18: =IF(F18="",CEILING(G18*(1+Settings!$B$4),5),MIN(F18,CEILING(G18*(1+Settings!$B$4),5))) -> 745 | N18: =IF(F18="","",1-G18/F18) -> 0.059093333
A19: MTN | B19: Awoof | C19: 2.5GB 2-Day Plan - 2 days | D19: 2 days | E19: 900.01 | F19: 900 | G19: 846.81 | H19: 900 | J19: =IF(I19="","",I19-G19) | K19: =IF(OR(I19="",I19=0),"",J19/I19) | L19: =IF(I19="","Set price",IF(I19<G19,"LOSS",IF(I19=G19,"Break-even","OK"))) -> Set price | M19: =IF(F19="",CEILING(G19*(1+Settings!$B$4),5),MIN(F19,CEILING(G19*(1+Settings!$B$4),5))) -> 890 | N19: =IF(F19="","",1-G19/F19) -> 0.0591
A20: MTN | B20: Awoof | C20: 3.2GB 2-Day Plan - 2 days | D20: 2 days | E20: 1000.01 | F20: 1000 | G20: 940.9 | H20: 1200 | J20: =IF(I20="","",I20-G20) | K20: =IF(OR(I20="",I20=0),"",J20/I20) | L20: =IF(I20="","Set price",IF(I20<G20,"LOSS",IF(I20=G20,"Break-even","OK"))) -> Set price | M20: =IF(F20="",CEILING(G20*(1+Settings!$B$4),5),MIN(F20,CEILING(G20*(1+Settings!$B$4),5))) -> 990 | N20: =IF(F20="","",1-G20/F20) -> 0.0591
A21: MTN | B21: Direct | C21: 500MB Weekly Plan - 7 days | D21: 7 days | E21: 500.02 | F21: 500 | G21: 470.45 | H21: 500 | J21: =IF(I21="","",I21-G21) | K21: =IF(OR(I21="",I21=0),"",J21/I21) | L21: =IF(I21="","Set price",IF(I21<G21,"LOSS",IF(I21=G21,"Break-even","OK"))) -> Set price | M21: =IF(F21="",CEILING(G21*(1+Settings!$B$4),5),MIN(F21,CEILING(G21*(1+Settings!$B$4),5))) -> 495 | N21: =IF(F21="","",1-G21/F21) -> 0.0591
A22: MTN | B22: Direct | C22: 1GB Weekly Plan - 7 days | D22: 7 days | E22: 800.01 | F22: 800 | G22: 752.72 | H22: 800 | J22: =IF(I22="","",I22-G22) | K22: =IF(OR(I22="",I22=0),"",J22/I22) | L22: =IF(I22="","Set price",IF(I22<G22,"LOSS",IF(I22=G22,"Break-even","OK"))) -> Set price | M22: =IF(F22="",CEILING(G22*(1+Settings!$B$4),5),MIN(F22,CEILING(G22*(1+Settings!$B$4),5))) -> 795 | N22: =IF(F22="","",1-G22/F22) -> 0.0591
A23: MTN | B23: Direct | C23: 1.5GB Weekly Plan - 7 days | D23: 7 days | E23: 1000.03 | F23: 1000 | G23: 940.9 | H23: 1000 | J23: =IF(I23="","",I23-G23) | K23: =IF(OR(I23="",I23=0),"",J23/I23) | L23: =IF(I23="","Set price",IF(I23<G23,"LOSS",IF(I23=G23,"Break-even","OK"))) -> Set price | M23: =IF(F23="",CEILING(G23*(1+Settings!$B$4),5),MIN(F23,CEILING(G23*(1+Settings!$B$4),5))) -> 990 | N23: =IF(F23="","",1-G23/F23) -> 0.0591
A24: MTN | B24: Direct | C24: 3.5GB Weekly Plan - 7 days | D24: 7 days | E24: 1500.03 | F24: 1500 | G24: 1411.35 | H24: 1500 | J24: =IF(I24="","",I24-G24) | K24: =IF(OR(I24="",I24=0),"",J24/I24) | L24: =IF(I24="","Set price",IF(I24<G24,"LOSS",IF(I24=G24,"Break-even","OK"))) -> Set price | M24: =IF(F24="",CEILING(G24*(1+Settings!$B$4),5),MIN(F24,CEILING(G24*(1+Settings!$B$4),5))) -> 1485 | N24: =IF(F24="","",1-G24/F24) -> 0.0591
A25: MTN | B25: Direct | C25: 6GB Weekly Plan - 7 days | D25: 7 days | E25: 2500.01 | F25: 2500 | G25: 2352.25 | H25: 2500 | J25: =IF(I25="","",I25-G25) | K25: =IF(OR(I25="",I25=0),"",J25/I25) | L25: =IF(I25="","Set price",IF(I25<G25,"LOSS",IF(I25=G25,"Break-even","OK"))) -> Set price | M25: =IF(F25="",CEILING(G25*(1+Settings!$B$4),5),MIN(F25,CEILING(G25*(1+Settings!$B$4),5))) -> 2470 | N25: =IF(F25="","",1-G25/F25) -> 0.0591
... A41: MTN | B41: Direct | C41: 480GB 3-Month Plan - 90 days | D41: 90 days | E41: 90000.03 | F41: 90000 | G41: 84681 | H41: 90000 | J41: =IF(I41="","",I41-G41) | K41: =IF(OR(I41="",I41=0),"",J41/I41) | L41: =IF(I41="","Set price",IF(I41<G41,"LOSS",IF(I41=G41,"Break-even","OK"))) -> Set price | M41: =IF(F41="",CEILING(G41*(1+Settings!$B$4),5),MIN(F41,CEILING(G41*(1+Settings!$B$4),5))) -> 88920 | N41: =IF(F41="","",1-G41/F41) -> 0.0591
A42: Glo | B42: SME | C42: 200 MB - 14 days | D42: 14 days | E42: 200 | G42: 94 | H42: 200 | J42: =IF(I42="","",I42-G42) | K42: =IF(OR(I42="",I42=0),"",J42/I42) | L42: =IF(I42="","Set price",IF(I42<G42,"LOSS",IF(I42=G42,"Break-even","OK"))) -> Set price | M42: =IF(F42="",CEILING(G42*(1+Settings!$B$4),5),MIN(F42,CEILING(G42*(1+Settings!$B$4),5))) -> 100 | N42: =IF(F42="","",1-G42/F42)
A43: Glo | B43: SME | C43: 500 MB - 7 days | D43: 7 days | E43: 500 | G43: 230 | H43: 250 | J43: =IF(I43="","",I43-G43) | K43: =IF(OR(I43="",I43=0),"",J43/I43) | L43: =IF(I43="","Set price",IF(I43<G43,"LOSS",IF(I43=G43,"Break-even","OK"))) -> Set price | M43: =IF(F43="",CEILING(G43*(1+Settings!$B$4),5),MIN(F43,CEILING(G43*(1+Settings!$B$4),5))) -> 245 | N43: =IF(F43="","",1-G43/F43)
A44: Glo | B44: SME | C44: 1 GB - 3 days | D44: 3 days | E44: 1000.11 | G44: 392 | H44: 370 | J44: =IF(I44="","",I44-G44) | K44: =IF(OR(I44="",I44=0),"",J44/I44) | L44: =IF(I44="","Set price",IF(I44<G44,"LOSS",IF(I44=G44,"Break-even","OK"))) -> Set price | M44: =IF(F44="",CEILING(G44*(1+Settings!$B$4),5),MIN(F44,CEILING(G44*(1+Settings!$B$4),5))) -> 415 | N44: =IF(F44="","",1-G44/F44)
A45: Glo | B45: SME | C45: 3 GB - 3 days | D45: 3 days | E45: 3000.11 | G45: 1176 | H45: 1095 | J45: =IF(I45="","",I45-G45) | K45: =IF(OR(I45="",I45=0),"",J45/I45) | L45: =IF(I45="","Set price",IF(I45<G45,"LOSS",IF(I45=G45,"Break-even","OK"))) -> Set price | M45: =IF(F45="",CEILING(G45*(1+Settings!$B$4),5),MIN(F45,CEILING(G45*(1+Settings!$B$4),5))) -> 1235 | N45: =IF(F45="","",1-G45/F45)
A46: Glo | B46: SME | C46: 5 GB - 3 days | D46: 3 days | E46: 5000.11 | G46: 1960 | H46: 1800 | J46: =IF(I46="","",I46-G46) | K46: =IF(OR(I46="",I46=0),"",J46/I46) | L46: =IF(I46="","Set price",IF(I46<G46,"LOSS",IF(I46=G46,"Break-even","OK"))) -> Set price | M46: =IF(F46="",CEILING(G46*(1+Settings!$B$4),5),MIN(F46,CEILING(G46*(1+Settings!$B$4),5))) -> 2060 | N46: =IF(F46="","",1-G46/F46)
A47: Glo | B47: SME | C47: 1 GB - 7 days | D47: 7 days | E47: 1000.12 | G47: 409 | H47: 400 | J47: =IF(I47="","",I47-G47) | K47: =IF(OR(I47="",I47=0),"",J47/I47) | L47: =IF(I47="","Set price",IF(I47<G47,"LOSS",IF(I47=G47,"Break-even","OK"))) -> Set price | M47: =IF(F47="",CEILING(G47*(1+Settings!$B$4),5),MIN(F47,CEILING(G47*(1+Settings!$B$4),5))) -> 430 | N47: =IF(F47="","",1-G47/F47)
A48: Glo | B48: SME | C48: 3 GB - 7 days | D48: 7 days | E48: 3000.12 | G48: 1228 | H48: 1095 | J48: =IF(I48="","",I48-G48) | K48: =IF(OR(I48="",I48=0),"",J48/I48) | L48: =IF(I48="","Set price",IF(I48<G48,"LOSS",IF(I48=G48,"Break-even","OK"))) -> Set price | M48: =IF(F48="",CEILING(G48*(1+Settings!$B$4),5),MIN(F48,CEILING(G48*(1+Settings!$B$4),5))) -> 1290 | N48: =IF(F48="","",1-G48/F48)
A49: Glo | B49: SME | C49: 5 GB - 7 days | D49: 7 days | E49: 5000.12 | G49: 2046 | H49: 1850 | J49: =IF(I49="","",I49-G49) | K49: =IF(OR(I49="",I49=0),"",J49/I49) | L49: =IF(I49="","Set price",IF(I49<G49,"LOSS",IF(I49=G49,"Break-even","OK"))) -> Set price | M49: =IF(F49="",CEILING(G49*(1+Settings!$B$4),5),MIN(F49,CEILING(G49*(1+Settings!$B$4),5))) -> 2150 | N49: =IF(F49="","",1-G49/F49)
A50: Glo | B50: SME | C50: 1 GB - 14 days Night Plan | D50: 14 days (night) | E50: 1000.21 | G50: 409 | H50: 400 | J50: =IF(I50="","",I50-G50) | K50: =IF(OR(I50="",I50=0),"",J50/I50) | L50: =IF(I50="","Set price",IF(I50<G50,"LOSS",IF(I50=G50,"Break-even","OK"))) -> Set price | M50: =IF(F50="",CEILING(G50*(1+Settings!$B$4),5),MIN(F50,CEILING(G50*(1+Settings!$B$4),5))) -> 430 | N50: =IF(F50="","",1-G50/F50)
A51: Glo | B51: SME | C51: 3 GB - 14 days Night Plan | D51: 14 days (night) | E51: 3000.21 | G51: 1228 | H51: 1100 | J51: =IF(I51="","",I51-G51) | K51: =IF(OR(I51="",I51=0),"",J51/I51) | L51: =IF(I51="","Set price",IF(I51<G51,"LOSS",IF(I51=G51,"Break-even","OK"))) -> Set price | M51: =IF(F51="",CEILING(G51*(1+Settings!$B$4),5),MIN(F51,CEILING(G51*(1+Settings!$B$4),5))) -> 1290 | N51: =IF(F51="","",1-G51/F51)
A52: Glo | B52: SME | C52: 5 GB - 14 days Night Plan | D52: 14 days (night) | E52: 5000.21 | G52: 2046 | H52: 2000 | J52: =IF(I52="","",I52-G52) | K52: =IF(OR(I52="",I52=0),"",J52/I52) | L52: =IF(I52="","Set price",IF(I52<G52,"LOSS",IF(I52=G52,"Break-even","OK"))) -> Set price | M52: =IF(F52="",CEILING(G52*(1+Settings!$B$4),5),MIN(F52,CEILING(G52*(1+Settings!$B$4),5))) -> 2150 | N52: =IF(F52="","",1-G52/F52)
A53: Glo | B53: SME | C53: 10 GB - 14 days Night Plan | D53: 14 days (night) | E53: 10000.21 | G53: 4093 | H53: 3650 | J53: =IF(I53="","",I53-G53) | K53: =IF(OR(I53="",I53=0),"",J53/I53) | L53: =IF(I53="","Set price",IF(I53<G53,"LOSS",IF(I53=G53,"Break-even","OK"))) -> Set price | M53: =IF(F53="",CEILING(G53*(1+Settings!$B$4),5),MIN(F53,CEILING(G53*(1+Settings!$B$4),5))) -> 4300 | N53: =IF(F53="","",1-G53/F53)
... A58: Glo | B58: SME | C58: 10 GB - 30 days | D58: 30 days | E58: 10000 | G58: 4612 | H58: 4700 | J58: =IF(I58="","",I58-G58) | K58: =IF(OR(I58="",I58=0),"",J58/I58) | L58: =IF(I58="","Set price",IF(I58<G58,"LOSS",IF(I58=G58,"Break-even","OK"))) -> Set price | M58: =IF(F58="",CEILING(G58*(1+Settings!$B$4),5),MIN(F58,CEILING(G58*(1+Settings!$B$4),5))) -> 4845 | N58: =IF(F58="","",1-G58/F58)
A59: Glo | B59: Awoof | C59: 125MB - 1 day | D59: 1 day | E59: 100.01 | F59: 100 | G59: 92.64 | H59: 120 | J59: =IF(I59="","",I59-G59) | K59: =IF(OR(I59="",I59=0),"",J59/I59) | L59: =IF(I59="","Set price",IF(I59<G59,"LOSS",IF(I59=G59,"Break-even","OK"))) -> Set price | M59: =IF(F59="",CEILING(G59*(1+Settings!$B$4),5),MIN(F59,CEILING(G59*(1+Settings!$B$4),5))) -> 100 | N59: =IF(F59="","",1-G59/F59) -> 0.0736
A60: Glo | B60: Awoof | C60: 260MB - 2 day | D60: 2 days | E60: 200.01 | F60: 200 | G60: 185.27 | H60: 220 | J60: =IF(I60="","",I60-G60) | K60: =IF(OR(I60="",I60=0),"",J60/I60) | L60: =IF(I60="","Set price",IF(I60<G60,"LOSS",IF(I60=G60,"Break-even","OK"))) -> Set price | M60: =IF(F60="",CEILING(G60*(1+Settings!$B$4),5),MIN(F60,CEILING(G60*(1+Settings!$B$4),5))) -> 195 | N60: =IF(F60="","",1-G60/F60) -> 0.07365
A61: Glo | B61: Direct | C61: 1.5GB - 14 days | D61: 14 days | E61: 500.01 | F61: 500 | G61: 463.18 | H61: 500 | J61: =IF(I61="","",I61-G61) | K61: =IF(OR(I61="",I61=0),"",J61/I61) | L61: =IF(I61="","Set price",IF(I61<G61,"LOSS",IF(I61=G61,"Break-even","OK"))) -> Set price | M61: =IF(F61="",CEILING(G61*(1+Settings!$B$4),5),MIN(F61,CEILING(G61*(1+Settings!$B$4),5))) -> 490 | N61: =IF(F61="","",1-G61/F61) -> 0.07364
A62: Glo | B62: Direct | C62: 2.6GB - 30 days | D62: 30 days | E62: 1000.01 | F62: 1000 | G62: 926.35 | H62: 1000 | J62: =IF(I62="","",I62-G62) | K62: =IF(OR(I62="",I62=0),"",J62/I62) | L62: =IF(I62="","Set price",IF(I62<G62,"LOSS",IF(I62=G62,"Break-even","OK"))) -> Set price | M62: =IF(F62="",CEILING(G62*(1+Settings!$B$4),5),MIN(F62,CEILING(G62*(1+Settings!$B$4),5))) -> 975 | N62: =IF(F62="","",1-G62/F62) -> 0.07365
A63: Glo | B63: Direct | C63: 5GB - 30 days | D63: 30 days | E63: 1500.01 | F63: 1500 | G63: 1389.53 | H63: 1500 | J63: =IF(I63="","",I63-G63) | K63: =IF(OR(I63="",I63=0),"",J63/I63) | L63: =IF(I63="","Set price",IF(I63<G63,"LOSS",IF(I63=G63,"Break-even","OK"))) -> Set price | M63: =IF(F63="",CEILING(G63*(1+Settings!$B$4),5),MIN(F63,CEILING(G63*(1+Settings!$B$4),5))) -> 1460 | N63: =IF(F63="","",1-G63/F63) -> 0.073646667
A64: Glo | B64: Direct | C64: 6.15GB - 30 days | D64: 30 days | E64: 2000.01 | F64: 2000 | G64: 1852.7 | H64: 2000 | J64: =IF(I64="","",I64-G64) | K64: =IF(OR(I64="",I64=0),"",J64/I64) | L64: =IF(I64="","Set price",IF(I64<G64,"LOSS",IF(I64=G64,"Break-even","OK"))) -> Set price | M64: =IF(F64="",CEILING(G64*(1+Settings!$B$4),5),MIN(F64,CEILING(G64*(1+Settings!$B$4),5))) -> 1950 | N64: =IF(F64="","",1-G64/F64) -> 0.07365
A65: Glo | B65: Direct | C65: 7.5GB - 30 days | D65: 30 days | E65: 2500.01 | F65: 2500 | G65: 2315.88 | H65: 2500 | J65: =IF(I65="","",I65-G65) | K65: =IF(OR(I65="",I65=0),"",J65/I65) | L65: =IF(I65="","Set price",IF(I65<G65,"LOSS",IF(I65=G65,"Break-even","OK"))) -> Set price | M65: =IF(F65="",CEILING(G65*(1+Settings!$B$4),5),MIN(F65,CEILING(G65*(1+Settings!$B$4),5))) -> 2435 | N65: =IF(F65="","",1-G65/F65) -> 0.073648
A66: Glo | B66: Direct | C66: 10GB - 30 days | D66: 30 days | E66: 3000.01 | F66: 3000 | G66: 2779.05 | H66: 3000 | J66: =IF(I66="","",I66-G66) | K66: =IF(OR(I66="",I66=0),"",J66/I66) | L66: =IF(I66="","Set price",IF(I66<G66,"LOSS",IF(I66=G66,"Break-even","OK"))) -> Set price | M66: =IF(F66="",CEILING(G66*(1+Settings!$B$4),5),MIN(F66,CEILING(G66*(1+Settings!$B$4),5))) -> 2920 | N66: =IF(F66="","",1-G66/F66) -> 0.07365
A67: Glo | B67: Direct | C67: 12.5GB - 30 days | D67: 30 days | E67: 4000.01 | F67: 4000 | G67: 3705.4 | H67: 4000 | J67: =IF(I67="","",I67-G67) | K67: =IF(OR(I67="",I67=0),"",J67/I67) | L67: =IF(I67="","Set price",IF(I67<G67,"LOSS",IF(I67=G67,"Break-even","OK"))) -> Set price | M67: =IF(F67="",CEILING(G67*(1+Settings!$B$4),5),MIN(F67,CEILING(G67*(1+Settings!$B$4),5))) -> 3895 | N67: =IF(F67="","",1-G67/F67) -> 0.07365
A68: Glo | B68: Direct | C68: 16GB - 30 days | D68: 30 days | E68: 5000.01 | F68: 5000 | G68: 4631.75 | H68: 5000 | J68: =IF(I68="","",I68-G68) | K68: =IF(OR(I68="",I68=0),"",J68/I68) | L68: =IF(I68="","Set price",IF(I68<G68,"LOSS",IF(I68=G68,"Break-even","OK"))) -> Set price | M68: =IF(F68="",CEILING(G68*(1+Settings!$B$4),5),MIN(F68,CEILING(G68*(1+Settings!$B$4),5))) -> 4865 | N68: =IF(F68="","",1-G68/F68) -> 0.07365
A69: Glo | B69: Direct | C69: 28GB - 30 days | D69: 30 days | E69: 8000.01 | F69: 8000 | G69: 7410.8 | H69: 8000 | J69: =IF(I69="","",I69-G69) | K69: =IF(OR(I69="",I69=0),"",J69/I69) | L69: =IF(I69="","Set price",IF(I69<G69,"LOSS",IF(I69=G69,"Break-even","OK"))) -> Set price | M69: =IF(F69="",CEILING(G69*(1+Settings!$B$4),5),MIN(F69,CEILING(G69*(1+Settings!$B$4),5))) -> 7785 | N69: =IF(F69="","",1-G69/F69) -> 0.07365
A70: Glo | B70: Direct | C70: 38GB - 30 days | D70: 30 days | E70: 10000.01 | F70: 10000 | G70: 9263.5 | H70: 10000 | J70: =IF(I70="","",I70-G70) | K70: =IF(OR(I70="",I70=0),"",J70/I70) | L70: =IF(I70="","Set price",IF(I70<G70,"LOSS",IF(I70=G70,"Break-even","OK"))) -> Set price | M70: =IF(F70="",CEILING(G70*(1+Settings!$B$4),5),MIN(F70,CEILING(G70*(1+Settings!$B$4),5))) -> 9730 | N70: =IF(F70="","",1-G70/F70) -> 0.07365
... A98: Airtel | B98: Direct | C98: 8GB - 30 days | D98: 30 days | E98: 2999.92 | F98: 3000 | G98: 2822.62 | H98: 3000 | J98: =IF(I98="","",I98-G98) | K98: =IF(OR(I98="",I98=0),"",J98/I98) | L98: =IF(I98="","Set price",IF(I98<G98,"LOSS",IF(I98=G98,"Break-even","OK"))) -> Set price | M98: =IF(F98="",CEILING(G98*(1+Settings!$B$4),5),MIN(F98,CEILING(G98*(1+Settings!$B$4),5))) -> 2965 | N98: =IF(F98="","",1-G98/F98) -> 0.059126667
A99: Airtel | B99: Direct | C99: 10GB - 30 days | D99: 30 days | E99: 3999.91 | F99: 4000 | G99: 3763.52 | J99: =IF(I99="","",I99-G99) | K99: =IF(OR(I99="",I99=0),"",J99/I99) | L99: =IF(I99="","Set price",IF(I99<G99,"LOSS",IF(I99=G99,"Break-even","OK"))) -> Set price | M99: =IF(F99="",CEILING(G99*(1+Settings!$B$4),5),MIN(F99,CEILING(G99*(1+Settings!$B$4),5))) -> 3955 | N99: =IF(F99="","",1-G99/F99) -> 0.05912
A100: Airtel | B100: Direct | C100: 13GB - 30 days | D100: 30 days | E100: 4999.92 | F100: 5000 | G100: 4704.42 | H100: 5000 | J100: =IF(I100="","",I100-G100) | K100: =IF(OR(I100="",I100=0),"",J100/I100) | L100: =IF(I100="","Set price",IF(I100<G100,"LOSS",IF(I100=G100,"Break-even","OK"))) -> Set price | M100: =IF(F100="",CEILING(G100*(1+Settings!$B$4),5),MIN(F100,CEILING(G100*(1+Settings!$B$4),5))) -> 4940 | N100: =IF(F100="","",1-G100/F100) -> 0.059116
A101: Airtel | B101: Direct | C101: 18GB - 30 days | D101: 30 days | E101: 5999.91 | F101: 6000 | G101: 5645.32 | J101: =IF(I101="","",I101-G101) | K101: =IF(OR(I101="",I101=0),"",J101/I101) | L101: =IF(I101="","Set price",IF(I101<G101,"LOSS",IF(I101=G101,"Break-even","OK"))) -> Set price | M101: =IF(F101="",CEILING(G101*(1+Settings!$B$4),5),MIN(F101,CEILING(G101*(1+Settings!$B$4),5))) -> 5930 | N101: =IF(F101="","",1-G101/F101) -> 0.059113333
A102: Airtel | B102: Direct | C102: 25GB - 30 days | D102: 30 days | E102: 7999.91 | F102: 8000 | G102: 7527.12 | H102: 8000 | J102: =IF(I102="","",I102-G102) | K102: =IF(OR(I102="",I102=0),"",J102/I102) | L102: =IF(I102="","Set price",IF(I102<G102,"LOSS",IF(I102=G102,"Break-even","OK"))) -> Set price | M102: =IF(F102="",CEILING(G102*(1+Settings!$B$4),5),MIN(F102,CEILING(G102*(1+Settings!$B$4),5))) -> 7905 | N102: =IF(F102="","",1-G102/F102) -> 0.05911
A103: Airtel | B103: Direct | C103: 35GB - 30 days | D103: 30 days | E103: 9999.91 | F103: 10000 | G103: 9408.92 | H103: 10000 | J103: =IF(I103="","",I103-G103) | K103: =IF(OR(I103="",I103=0),"",J103/I103) | L103: =IF(I103="","Set price",IF(I103<G103,"LOSS",IF(I103=G103,"Break-even","OK"))) -> Set price | M103: =IF(F103="",CEILING(G103*(1+Settings!$B$4),5),MIN(F103,CEILING(G103*(1+Settings!$B$4),5))) -> 9880 | N103: =IF(F103="","",1-G103/F103) -> 0.059108
A104: Airtel | B104: Direct | C104: 60GB - 30 days | D104: 30 days | E104: 14999.91 | F104: 15000 | G104: 14113.42 | H104: 15000 | J104: =IF(I104="","",I104-G104) | K104: =IF(OR(I104="",I104=0),"",J104/I104) | L104: =IF(I104="","Set price",IF(I104<G104,"LOSS",IF(I104=G104,"Break-even","OK"))) -> Set price | M104: =IF(F104="",CEILING(G104*(1+Settings!$B$4),5),MIN(F104,CEILING(G104*(1+Settings!$B$4),5))) -> 14820 | N104: =IF(F104="","",1-G104/F104) -> 0.059105333
A105: Airtel | B105: Direct | C105: 100GB - 30 days | D105: 30 days | E105: 19999.91 | F105: 20000 | G105: 18817.92 | H105: 20000 | J105: =IF(I105="","",I105-G105) | K105: =IF(OR(I105="",I105=0),"",J105/I105) | L105: =IF(I105="","Set price",IF(I105<G105,"LOSS",IF(I105=G105,"Break-even","OK"))) -> Set price | M105: =IF(F105="",CEILING(G105*(1+Settings!$B$4),5),MIN(F105,CEILING(G105*(1+Settings!$B$4),5))) -> 19760 | N105: =IF(F105="","",1-G105/F105) -> 0.059104
A106: Airtel | B106: Direct | C106: 160GB - 30 days | D106: 30 days | E106: 29999.91 | F106: 30000 | G106: 28226.92 | H106: 30000 | J106: =IF(I106="","",I106-G106) | K106: =IF(OR(I106="",I106=0),"",J106/I106) | L106: =IF(I106="","Set price",IF(I106<G106,"LOSS",IF(I106=G106,"Break-even","OK"))) -> Set price | M106: =IF(F106="",CEILING(G106*(1+Settings!$B$4),5),MIN(F106,CEILING(G106*(1+Settings!$B$4),5))) -> 29640 | N106: =IF(F106="","",1-G106/F106) -> 0.059102667
A107: Airtel | B107: Direct | C107: 210GB - 30 days | D107: 30 days | E107: 39999.91 | F107: 40000 | G107: 37635.92 | H107: 40000 | J107: =IF(I107="","",I107-G107) | K107: =IF(OR(I107="",I107=0),"",J107/I107) | L107: =IF(I107="","Set price",IF(I107<G107,"LOSS",IF(I107=G107,"Break-even","OK"))) -> Set price | M107: =IF(F107="",CEILING(G107*(1+Settings!$B$4),5),MIN(F107,CEILING(G107*(1+Settings!$B$4),5))) -> 39520 | N107: =IF(F107="","",1-G107/F107) -> 0.059102
A108: Airtel | B108: Direct | C108: 300GB - 90 days | D108: 90 days | E108: 49999.91 | F108: 50000 | G108: 47044.92 | H108: 50000 | J108: =IF(I108="","",I108-G108) | K108: =IF(OR(I108="",I108=0),"",J108/I108) | L108: =IF(I108="","Set price",IF(I108<G108,"LOSS",IF(I108=G108,"Break-even","OK"))) -> Set price | M108: =IF(F108="",CEILING(G108*(1+Settings!$B$4),5),MIN(F108,CEILING(G108*(1+Settings!$B$4),5))) -> 49400 | N108: =IF(F108="","",1-G108/F108) -> 0.0591016
A109: Airtel | B109: Direct | C109: 350GB - 90 days | D109: 90 days | E109: 59999.91 | F109: 60000 | G109: 56453.92 | H109: 60000 | J109: =IF(I109="","",I109-G109) | K109: =IF(OR(I109="",I109=0),"",J109/I109) | L109: =IF(I109="","Set price",IF(I109<G109,"LOSS",IF(I109=G109,"Break-even","OK"))) -> Set price | M109: =IF(F109="",CEILING(G109*(1+Settings!$B$4),5),MIN(F109,CEILING(G109*(1+Settings!$B$4),5))) -> 59280 | N109: =IF(F109="","",1-G109/F109) -> 0.059101333
A110: 9mobile | B110: SME | C110: 50 MB - 30 days | D110: 30 days | E110: 50 | G110: 25 | H110: 50 | J110: =IF(I110="","",I110-G110) | K110: =IF(OR(I110="",I110=0),"",J110/I110) | L110: =IF(I110="","Set price",IF(I110<G110,"LOSS",IF(I110=G110,"Break-even","OK"))) -> Set price | M110: =IF(F110="",CEILING(G110*(1+Settings!$B$4),5),MIN(F110,CEILING(G110*(1+Settings!$B$4),5))) -> 30 | N110: =IF(F110="","",1-G110/F110)
A111: 9mobile | B111: SME | C111: 100 MB - 30 days | D111: 30 days | E111: 100 | G111: 51 | H111: 100 | J111: =IF(I111="","",I111-G111) | K111: =IF(OR(I111="",I111=0),"",J111/I111) | L111: =IF(I111="","Set price",IF(I111<G111,"LOSS",IF(I111=G111,"Break-even","OK"))) -> Set price | M111: =IF(F111="",CEILING(G111*(1+Settings!$B$4),5),MIN(F111,CEILING(G111*(1+Settings!$B$4),5))) -> 55 | N111: =IF(F111="","",1-G111/F111)
A112: 9mobile | B112: SME | C112: 300 MB - 30 days | D112: 30 days | E112: 300 | G112: 153 | H112: 250 | J112: =IF(I112="","",I112-G112) | K112: =IF(OR(I112="",I112=0),"",J112/I112) | L112: =IF(I112="","Set price",IF(I112<G112,"LOSS",IF(I112=G112,"Break-even","OK"))) -> Set price | M112: =IF(F112="",CEILING(G112*(1+Settings!$B$4),5),MIN(F112,CEILING(G112*(1+Settings!$B$4),5))) -> 165 | N112: =IF(F112="","",1-G112/F112)
A113: 9mobile | B113: SME | C113: 500 MB - 30 days | D113: 30 days | E113: 500 | G113: 246 | H113: 350 | J113: =IF(I113="","",I113-G113) | K113: =IF(OR(I113="",I113=0),"",J113/I113) | L113: =IF(I113="","Set price",IF(I113<G113,"LOSS",IF(I113=G113,"Break-even","OK"))) -> Set price | M113: =IF(F113="",CEILING(G113*(1+Settings!$B$4),5),MIN(F113,CEILING(G113*(1+Settings!$B$4),5))) -> 260 | N113: =IF(F113="","",1-G113/F113)
A114: 9mobile | B114: SME | C114: 1 GB - 30 days | D114: 30 days | E114: 1000 | G114: 492 | H114: 600 | J114: =IF(I114="","",I114-G114) | K114: =IF(OR(I114="",I114=0),"",J114/I114) | L114: =IF(I114="","Set price",IF(I114<G114,"LOSS",IF(I114=G114,"Break-even","OK"))) -> Set price | M114: =IF(F114="",CEILING(G114*(1+Settings!$B$4),5),MIN(F114,CEILING(G114*(1+Settings!$B$4),5))) -> 520 | N114: =IF(F114="","",1-G114/F114)
A115: 9mobile | B115: SME | C115: 2 GB - 30 days | D115: 30 days | E115: 2000 | G115: 984 | H115: 1200 | J115: =IF(I115="","",I115-G115) | K115: =IF(OR(I115="",I115=0),"",J115/I115) | L115: =IF(I115="","Set price",IF(I115<G115,"LOSS",IF(I115=G115,"Break-even","OK"))) -> Set price | M115: =IF(F115="",CEILING(G115*(1+Settings!$B$4),5),MIN(F115,CEILING(G115*(1+Settings!$B$4),5))) -> 1035 | N115: =IF(F115="","",1-G115/F115)
A116: 9mobile | B116: SME | C116: 3 GB - 30 days | D116: 30 days | E116: 3000 | G116: 1476 | H116: 1650 | J116: =IF(I116="","",I116-G116) | K116: =IF(OR(I116="",I116=0),"",J116/I116) | L116: =IF(I116="","Set price",IF(I116<G116,"LOSS",IF(I116=G116,"Break-even","OK"))) -> Set price | M116: =IF(F116="",CEILING(G116*(1+Settings!$B$4),5),MIN(F116,CEILING(G116*(1+Settings!$B$4),5))) -> 1550 | N116: =IF(F116="","",1-G116/F116)
A117: 9mobile | B117: SME | C117: 4 GB - 30 days | D117: 30 days | E117: 4000 | G117: 1968 | H117: 2100 | J117: =IF(I117="","",I117-G117) | K117: =IF(OR(I117="",I117=0),"",J117/I117) | L117: =IF(I117="","Set price",IF(I117<G117,"LOSS",IF(I117=G117,"Break-even","OK"))) -> Set price | M117: =IF(F117="",CEILING(G117*(1+Settings!$B$4),5),MIN(F117,CEILING(G117*(1+Settings!$B$4),5))) -> 2070 | N117: =IF(F117="","",1-G117/F117)
A118: 9mobile | B118: SME | C118: 5 GB - 30 days | D118: 30 days | E118: 5000 | G118: 2460 | H118: 2600 | J118: =IF(I118="","",I118-G118) | K118: =IF(OR(I118="",I118=0),"",J118/I118) | L118: =IF(I118="","Set price",IF(I118<G118,"LOSS",IF(I118=G118,"Break-even","OK"))) -> Set price | M118: =IF(F118="",CEILING(G118*(1+Settings!$B$4),5),MIN(F118,CEILING(G118*(1+Settings!$B$4),5))) -> 2585 | N118: =IF(F118="","",1-G118/F118)
A119: 9mobile | B119: SME | C119: 10 GB - 30 days | D119: 30 days | E119: 10000 | G119: 4920 | H119: 5000 | J119: =IF(I119="","",I119-G119) | K119: =IF(OR(I119="",I119=0),"",J119/I119) | L119: =IF(I119="","Set price",IF(I119<G119,"LOSS",IF(I119=G119,"Break-even","OK"))) -> Set price | M119: =IF(F119="",CEILING(G119*(1+Settings!$B$4),5),MIN(F119,CEILING(G119*(1+Settings!$B$4),5))) -> 5170 | N119: =IF(F119="","",1-G119/F119)
A120: 9mobile | B120: SME | C120: 15 GB - 30 days | D120: 30 days | E120: 15000 | G120: 7380 | H120: 7500 | J120: =IF(I120="","",I120-G120) | K120: =IF(OR(I120="",I120=0),"",J120/I120) | L120: =IF(I120="","Set price",IF(I120<G120,"LOSS",IF(I120=G120,"Break-even","OK"))) -> Set price | M120: =IF(F120="",CEILING(G120*(1+Settings!$B$4),5),MIN(F120,CEILING(G120*(1+Settings!$B$4),5))) -> 7750 | N120: =IF(F120="","",1-G120/F120)
A121: 9mobile | B121: SME | C121: 20 GB - 30 days | D121: 30 days | E121: 20000 | G121: 9840 | H121: 10000 | J121: =IF(I121="","",I121-G121) | K121: =IF(OR(I121="",I121=0),"",J121/I121) | L121: =IF(I121="","Set price",IF(I121<G121,"LOSS",IF(I121=G121,"Break-even","OK"))) -> Set price | M121: =IF(F121="",CEILING(G121*(1+Settings!$B$4),5),MIN(F121,CEILING(G121*(1+Settings!$B$4),5))) -> 10335 | N121: =IF(F121="","",1-G121/F121)
A122: 9mobile | B122: SME | C122: 25 GB - 30 days | D122: 30 days | E122: 25000 | G122: 12300 | H122: 13000 | J122: =IF(I122="","",I122-G122) | K122: =IF(OR(I122="",I122=0),"",J122/I122) | L122: =IF(I122="","Set price",IF(I122<G122,"LOSS",IF(I122=G122,"Break-even","OK"))) -> Set price | M122: =IF(F122="",CEILING(G122*(1+Settings!$B$4),5),MIN(F122,CEILING(G122*(1+Settings!$B$4),5))) -> 12915 | N122: =IF(F122="","",1-G122/F122)
A123: 9mobile | B123: Awoof | C123: 100MB - 1 day | D123: 1 day | E123: 100.01 | F123: 100 | G123: 86.49 | H123: 120 | J123: =IF(I123="","",I123-G123) | K123: =IF(OR(I123="",I123=0),"",J123/I123) | L123: =IF(I123="","Set price",IF(I123<G123,"LOSS",IF(I123=G123,"Break-even","OK"))) -> Set price | M123: =IF(F123="",CEILING(G123*(1+Settings!$B$4),5),MIN(F123,CEILING(G123*(1+Settings!$B$4),5))) -> 95 | N123: =IF(F123="","",1-G123/F123) -> 0.1351
A124: 9mobile | B124: Awoof | C124: 180MB - 1 days | D124: 1 day | E124: 150.01 | F124: 150 | G124: 129.74 | H124: 170 | J124: =IF(I124="","",I124-G124) | K124: =IF(OR(I124="",I124=0),"",J124/I124) | L124: =IF(I124="","Set price",IF(I124<G124,"LOSS",IF(I124=G124,"Break-even","OK"))) -> Set price | M124: =IF(F124="",CEILING(G124*(1+Settings!$B$4),5),MIN(F124,CEILING(G124*(1+Settings!$B$4),5))) -> 140 | N124: =IF(F124="","",1-G124/F124) -> 0.13506667
A125: 9mobile | B125: Awoof | C125: 250MB - 1 days | D125: 1 day | E125: 200.01 | F125: 200 | G125: 172.98 | J125: =IF(I125="","",I125-G125) | K125: =IF(OR(I125="",I125=0),"",J125/I125) | L125: =IF(I125="","Set price",IF(I125<G125,"LOSS",IF(I125=G125,"Break-even","OK"))) -> Set price | M125: =IF(F125="",CEILING(G125*(1+Settings!$B$4),5),MIN(F125,CEILING(G125*(1+Settings!$B$4),5))) -> 185 | N125: =IF(F125="","",1-G125/F125) -> 0.1351
A126: 9mobile | B126: Awoof | C126: 450MB - 1 day | D126: 1 day | E126: 350.01 | F126: 350 | G126: 302.72 | H126: 400 | J126: =IF(I126="","",I126-G126) | K126: =IF(OR(I126="",I126=0),"",J126/I126) | L126: =IF(I126="","Set price",IF(I126<G126,"LOSS",IF(I126=G126,"Break-even","OK"))) -> Set price | M126: =IF(F126="",CEILING(G126*(1+Settings!$B$4),5),MIN(F126,CEILING(G126*(1+Settings!$B$4),5))) -> 320 | N126: =IF(F126="","",1-G126/F126) -> 0.13508571
A127: 9mobile | B127: Awoof | C127: 650MB - 3 days | D127: 3 days | E127: 500.01 | F127: 500 | G127: 432.45 | H127: 500 | J127: =IF(I127="","",I127-G127) | K127: =IF(OR(I127="",I127=0),"",J127/I127) | L127: =IF(I127="","Set price",IF(I127<G127,"LOSS",IF(I127=G127,"Break-even","OK"))) -> Set price | M127: =IF(F127="",CEILING(G127*(1+Settings!$B$4),5),MIN(F127,CEILING(G127*(1+Settings!$B$4),5))) -> 455 | N127: =IF(F127="","",1-G127/F127) -> 0.1351
A128: 9mobile | B128: Direct | C128: 1.75GB - 7 days | D128: 7 days | E128: 1500.01 | F128: 1500 | G128: 1297.35 | H128: 1500 | J128: =IF(I128="","",I128-G128) | K128: =IF(OR(I128="",I128=0),"",J128/I128) | L128: =IF(I128="","Set price",IF(I128<G128,"LOSS",IF(I128=G128,"Break-even","OK"))) -> Set price | M128: =IF(F128="",CEILING(G128*(1+Settings!$B$4),5),MIN(F128,CEILING(G128*(1+Settings!$B$4),5))) -> 1365 | N128: =IF(F128="","",1-G128/F128) -> 0.1351
A129: 9mobile | B129: Direct | C129: 650MB - 14 days | D129: 14 days | E129: 600.01 | F129: 600 | G129: 518.94 | H129: 600 | J129: =IF(I129="","",I129-G129) | K129: =IF(OR(I129="",I129=0),"",J129/I129) | L129: =IF(I129="","Set price",IF(I129<G129,"LOSS",IF(I129=G129,"Break-even","OK"))) -> Set price | M129: =IF(F129="",CEILING(G129*(1+Settings!$B$4),5),MIN(F129,CEILING(G129*(1+Settings!$B$4),5))) -> 545 | N129: =IF(F129="","",1-G129/F129) -> 0.1351
A130: 9mobile | B130: Direct | C130: 1.1GB - 30 days | D130: 30 days | E130: 1000.01 | F130: 1000 | G130: 864.9 | H130: 1000 | J130: =IF(I130="","",I130-G130) | K130: =IF(OR(I130="",I130=0),"",J130/I130) | L130: =IF(I130="","Set price",IF(I130<G130,"LOSS",IF(I130=G130,"Break-even","OK"))) -> Set price | M130: =IF(F130="",CEILING(G130*(1+Settings!$B$4),5),MIN(F130,CEILING(G130*(1+Settings!$B$4),5))) -> 910 | N130: =IF(F130="","",1-G130/F130) -> 0.1351
A131: 9mobile | B131: Direct | C131: 1.4GB - 30 days | D131: 30 days | E131: 1200.01 | F131: 1200 | G131: 1037.88 | H131: 1200 | J131: =IF(I131="","",I131-G131) | K131: =IF(OR(I131="",I131=0),"",J131/I131) | L131: =IF(I131="","Set price",IF(I131<G131,"LOSS",IF(I131=G131,"Break-even","OK"))) -> Set price | M131: =IF(F131="",CEILING(G131*(1+Settings!$B$4),5),MIN(F131,CEILING(G131*(1+Settings!$B$4),5))) -> 1090 | N131: =IF(F131="","",1-G131/F131) -> 0.1351
A132: 9mobile | B132: Direct | C132: 2.44GB - 30 days | D132: 30 days | E132: 2000.01 | F132: 2000 | G132: 1729.8 | H132: 2000 | J132: =IF(I132="","",I132-G132) | K132: =IF(OR(I132="",I132=0),"",J132/I132) | L132: =IF(I132="","Set price",IF(I132<G132,"LOSS",IF(I132=G132,"Break-even","OK"))) -> Set price | M132: =IF(F132="",CEILING(G132*(1+Settings!$B$4),5),MIN(F132,CEILING(G132*(1+Settings!$B$4),5))) -> 1820 | N132: =IF(F132="","",1-G132/F132) -> 0.1351
A133: 9mobile | B133: Direct | C133: 3.17GB - 30 days | D133: 30 days | E133: 2500.01 | F133: 2500 | G133: 2162.25 | H133: 2500 | J133: =IF(I133="","",I133-G133) | K133: =IF(OR(I133="",I133=0),"",J133/I133) | L133: =IF(I133="","Set price",IF(I133<G133,"LOSS",IF(I133=G133,"Break-even","OK"))) -> Set price | M133: =IF(F133="",CEILING(G133*(1+Settings!$B$4),5),MIN(F133,CEILING(G133*(1+Settings!$B$4),5))) -> 2275 | N133: =IF(F133="","",1-G133/F133) -> 0.1351
A134: 9mobile | B134: Direct | C134: 3.91GB - 30 days | D134: 30 days | E134: 3000.01 | F134: 3000 | G134: 2594.7 | H134: 3000 | J134: =IF(I134="","",I134-G134) | K134: =IF(OR(I134="",I134=0),"",J134/I134) | L134: =IF(I134="","Set price",IF(I134<G134,"LOSS",IF(I134=G134,"Break-even","OK"))) -> Set price | M134: =IF(F134="",CEILING(G134*(1+Settings!$B$4),5),MIN(F134,CEILING(G134*(1+Settings!$B$4),5))) -> 2725 | N134: =IF(F134="","",1-G134/F134) -> 0.1351
A135: 9mobile | B135: Direct | C135: 5.10GB - 30 days | D135: 30 days | E135: 4000.01 | F135: 4000 | G135: 3459.6 | H135: 4000 | J135: =IF(I135="","",I135-G135) | K135: =IF(OR(I135="",I135=0),"",J135/I135) | L135: =IF(I135="","Set price",IF(I135<G135,"LOSS",IF(I135=G135,"Break-even","OK"))) -> Set price | M135: =IF(F135="",CEILING(G135*(1+Settings!$B$4),5),MIN(F135,CEILING(G135*(1+Settings!$B$4),5))) -> 3635 | N135: =IF(F135="","",1-G135/F135) -> 0.1351
A136: 9mobile | B136: Direct | C136: 6.5GB - 30 days | D136: 30 days | E136: 5000.01 | F136: 5000 | G136: 4324.5 | H136: 5000 | J136: =IF(I136="","",I136-G136) | K136: =IF(OR(I136="",I136=0),"",J136/I136) | L136: =IF(I136="","Set price",IF(I136<G136,"LOSS",IF(I136=G136,"Break-even","OK"))) -> Set price | M136: =IF(F136="",CEILING(G136*(1+Settings!$B$4),5),MIN(F136,CEILING(G136*(1+Settings!$B$4),5))) -> 4545 | N136: =IF(F136="","",1-G136/F136) -> 0.1351
A137: 9mobile | B137: Direct | C137: 16GB - 30 days | D137: 30 days | E137: 12000.01 | F137: 12000 | G137: 10378.8 | H137: 11800 | J137: =IF(I137="","",I137-G137) | K137: =IF(OR(I137="",I137=0),"",J137/I137) | L137: =IF(I137="","Set price",IF(I137<G137,"LOSS",IF(I137=G137,"Break-even","OK"))) -> Set price | M137: =IF(F137="",CEILING(G137*(1+Settings!$B$4),5),MIN(F137,CEILING(G137*(1+Settings!$B$4),5))) -> 10900 | N137: =IF(F137="","",1-G137/F137) -> 0.1351
... A140: 9mobile | B140: Direct | C140: 39GB - 60 days | D140: 60 days | E140: 30000.01 | F140: 30000 | G140: 25947 | H140: 30000 | J140: =IF(I140="","",I140-G140) | K140: =IF(OR(I140="",I140=0),"",J140/I140) | L140: =IF(I140="","Set price",IF(I140<G140,"LOSS",IF(I140=G140,"Break-even","OK"))) -> Set price | M140: =IF(F140="",CEILING(G140*(1+Settings!$B$4),5),MIN(F140,CEILING(G140*(1+Settings!$B$4),5))) -> 27245 | N140: =IF(F140="","",1-G140/F140) -> 0.1351
A142: Source: Live from ClubKonnect via KudiTrack's clubkonnect edge function (GitHub Actions run 36193015699), 25 Sep 2026, 21:43 WAT. Costs are per plan, in naira.

Sheet Print Data
A1: Print data (data PINs): cost per PIN and your sale price
A2: Same ClubKonnect plan list as direct data · 25 Sep 2026, 21:43 WAT
A4: Network | B4: Type | C4: Plan | D4: Validity | E4: CK plan ID | F4: ClubKonnect cost per PIN (₦) | G4: YOUR SALE PRICE PER PIN (₦) | H4: Profit per PIN (₦) | I4: Margin | J4: Status | K4: Profit per 100 PINs (₦) | L4: Suggested price (₦)
A5: MTN | B5: SME | C5: 500 MB - Weekly | D5: 7 days | E5: 500 | F5: ='Data Plans'!G5 -> 297 | H5: =IF(G5="","",G5-F5) | I5: =IF(OR(G5="",G5=0),"",H5/G5) | J5: =IF(G5="","Set price",IF(G5<F5,"LOSS",IF(G5=F5,"Break-even","OK"))) -> Set price | K5: =IF(H5="","",H5*100) | L5: =CEILING(F5*(1+Settings!$B$4),5) -> 315
A6: MTN | B6: SME | C6: 500 MB - Monthly | D6: 30 days | E6: 500.00 | F6: ='Data Plans'!G6 -> 307 | H6: =IF(G6="","",G6-F6) | I6: =IF(OR(G6="",G6=0),"",H6/G6) | J6: =IF(G6="","Set price",IF(G6<F6,"LOSS",IF(G6=F6,"Break-even","OK"))) -> Set price | K6: =IF(H6="","",H6*100) | L6: =CEILING(F6*(1+Settings!$B$4),5) -> 325
A7: MTN | B7: SME | C7: 1 GB - Weekly | D7: 7 days | E7: 1000 | F7: ='Data Plans'!G7 -> 410 | H7: =IF(G7="","",G7-F7) | I7: =IF(OR(G7="",G7=0),"",H7/G7) | J7: =IF(G7="","Set price",IF(G7<F7,"LOSS",IF(G7=F7,"Break-even","OK"))) -> Set price | K7: =IF(H7="","",H7*100) | L7: =CEILING(F7*(1+Settings!$B$4),5) -> 435
A8: MTN | B8: SME | C8: 1 GB - Monthly | D8: 30 days | E8: 1000.00 | F8: ='Data Plans'!G8 -> 563 | H8: =IF(G8="","",G8-F8) | I8: =IF(OR(G8="",G8=0),"",H8/G8) | J8: =IF(G8="","Set price",IF(G8<F8,"LOSS",IF(G8=F8,"Break-even","OK"))) -> Set price | K8: =IF(H8="","",H8*100) | L8: =CEILING(F8*(1+Settings!$B$4),5) -> 595
A9: MTN | B9: SME | C9: 2 GB - Weekly | D9: 7 days | E9: 2000 | F9: ='Data Plans'!G9 -> 820 | H9: =IF(G9="","",G9-F9) | I9: =IF(OR(G9="",G9=0),"",H9/G9) | J9: =IF(G9="","Set price",IF(G9<F9,"LOSS",IF(G9=F9,"Break-even","OK"))) -> Set price | K9: =IF(H9="","",H9*100) | L9: =CEILING(F9*(1+Settings!$B$4),5) -> 865
A10: MTN | B10: SME | C10: 2 GB - Monthly | D10: 30 days | E10: 2000.00 | F10: ='Data Plans'!G10 -> 1117 | H10: =IF(G10="","",G10-F10) | I10: =IF(OR(G10="",G10=0),"",H10/G10) | J10: =IF(G10="","Set price",IF(G10<F10,"LOSS",IF(G10=F10,"Break-even","OK"))) -> Set price | K10: =IF(H10="","",H10*100) | L10: =CEILING(F10*(1+Settings!$B$4),5) -> 1175
A11: MTN | B11: SME | C11: 3 GB - Weekly | D11: 7 days | E11: 3000 | F11: ='Data Plans'!G11 -> 1230 | H11: =IF(G11="","",G11-F11) | I11: =IF(OR(G11="",G11=0),"",H11/G11) | J11: =IF(G11="","Set price",IF(G11<F11,"LOSS",IF(G11=F11,"Break-even","OK"))) -> Set price | K11: =IF(H11="","",H11*100) | L11: =CEILING(F11*(1+Settings!$B$4),5) -> 1295
A12: MTN | B12: SME | C12: 3 GB - Monthly | D12: 30 days | E12: 3000.00 | F12: ='Data Plans'!G12 -> 1629 | H12: =IF(G12="","",G12-F12) | I12: =IF(OR(G12="",G12=0),"",H12/G12) | J12: =IF(G12="","Set price",IF(G12<F12,"LOSS",IF(G12=F12,"Break-even","OK"))) -> Set price | K12: =IF(H12="","",H12*100) | L12: =CEILING(F12*(1+Settings!$B$4),5) -> 1715
A13: MTN | B13: SME | C13: 5 GB - Monthly | D13: 30 days | E13: 5000.00 | F13: ='Data Plans'!G13 -> 2511 | H13: =IF(G13="","",G13-F13) | I13: =IF(OR(G13="",G13=0),"",H13/G13) | J13: =IF(G13="","Set price",IF(G13<F13,"LOSS",IF(G13=F13,"Break-even","OK"))) -> Set price | K13: =IF(H13="","",H13*100) | L13: =CEILING(F13*(1+Settings!$B$4),5) -> 2640
A14: MTN | B14: Awoof | C14: 110MB Daily Plan - 1 day | D14: 1 day | E14: 100.01 | F14: ='Data Plans'!G14 -> 94.09 | H14: =IF(G14="","",G14-F14) | I14: =IF(OR(G14="",G14=0),"",H14/G14) | J14: =IF(G14="","Set price",IF(G14<F14,"LOSS",IF(G14=F14,"Break-even","OK"))) -> Set price | K14: =IF(H14="","",H14*100) | L14: =CEILING(F14*(1+Settings!$B$4),5) -> 100
A15: MTN | B15: Awoof | C15: 230MB Daily Plan - 1 day | D15: 1 day | E15: 200.01 | F15: ='Data Plans'!G15 -> 188.18 | H15: =IF(G15="","",G15-F15) | I15: =IF(OR(G15="",G15=0),"",H15/G15) | J15: =IF(G15="","Set price",IF(G15<F15,"LOSS",IF(G15=F15,"Break-even","OK"))) -> Set price | K15: =IF(H15="","",H15*100) | L15: =CEILING(F15*(1+Settings!$B$4),5) -> 200
A16: MTN | B16: Awoof | C16: 500MB Daily Plan - 1 day | D16: 1 day | E16: 350.01 | F16: ='Data Plans'!G16 -> 329.32 | H16: =IF(G16="","",G16-F16) | I16: =IF(OR(G16="",G16=0),"",H16/G16) | J16: =IF(G16="","Set price",IF(G16<F16,"LOSS",IF(G16=F16,"Break-even","OK"))) -> Set price | K16: =IF(H16="","",H16*100) | L16: =CEILING(F16*(1+Settings!$B$4),5) -> 350
... A140: 9mobile | B140: Direct | C140: 39GB - 60 days | D140: 60 days | E140: 30000.01 | F140: ='Data Plans'!G140 -> 25947 | H140: =IF(G140="","",G140-F140) | I140: =IF(OR(G140="",G140=0),"",H140/G140) | J140: =IF(G140="","Set price",IF(G140<F140,"LOSS",IF(G140=F140,"Break-even","OK"))) -> Set price | K140: =IF(H140="","",H140*100) | L140: =CEILING(F140*(1+Settings!$B$4),5) -> 27245
A142: Cost per PIN is linked from 'Data Plans' (green). The app prices print data at the same unit cost as direct data.

Sheet Airtime Print
A1: Print airtime (recharge card PINs): cost per PIN and your sale price
A2: Denominations offered in the app: ₦100, ₦200, ₦300, ₦500, ₦1000 · 25 Sep 2026, 21:43 WAT
A4: Network | B4: Face value (₦) | C4: CK print discount | D4: ClubKonnect cost per PIN (₦) | E4: Current KudiTrack price (₦) | F4: YOUR SALE PRICE PER PIN (₦) | G4: Profit per PIN (₦) | H4: Margin | I4: Status | J4: Profit per 100 PINs (₦) | K4: Suggested price (₦)
A5: MTN | B5: 100 | C5: =Settings!$C$9 -> 0.01 | D5: =B5*(1-C5) -> 99 | E5: =CEILING(D5*(1+Settings!$B$5),1) -> 100 | G5: =IF(F5="","",F5-D5) | H5: =IF(OR(F5="",F5=0),"",G5/F5) | I5: =IF(F5="","Set price",IF(F5<D5,"LOSS",IF(F5=D5,"Break-even","OK"))) -> Set price | J5: =IF(G5="","",G5*100) | K5: =MIN(B5,CEILING(D5*(1+Settings!$B$4),1)) -> 100
A6: MTN | B6: 200 | C6: =Settings!$C$9 -> 0.01 | D6: =B6*(1-C6) -> 198 | E6: =CEILING(D6*(1+Settings!$B$5),1) -> 200 | G6: =IF(F6="","",F6-D6) | H6: =IF(OR(F6="",F6=0),"",G6/F6) | I6: =IF(F6="","Set price",IF(F6<D6,"LOSS",IF(F6=D6,"Break-even","OK"))) -> Set price | J6: =IF(G6="","",G6*100) | K6: =MIN(B6,CEILING(D6*(1+Settings!$B$4),1)) -> 200
A7: MTN | B7: 300 | C7: =Settings!$C$9 -> 0.01 | D7: =B7*(1-C7) -> 297 | E7: =CEILING(D7*(1+Settings!$B$5),1) -> 300 | G7: =IF(F7="","",F7-D7) | H7: =IF(OR(F7="",F7=0),"",G7/F7) | I7: =IF(F7="","Set price",IF(F7<D7,"LOSS",IF(F7=D7,"Break-even","OK"))) -> Set price | J7: =IF(G7="","",G7*100) | K7: =MIN(B7,CEILING(D7*(1+Settings!$B$4),1)) -> 300
A8: MTN | B8: 500 | C8: =Settings!$C$9 -> 0.01 | D8: =B8*(1-C8) -> 495 | E8: =CEILING(D8*(1+Settings!$B$5),1) -> 500 | G8: =IF(F8="","",F8-D8) | H8: =IF(OR(F8="",F8=0),"",G8/F8) | I8: =IF(F8="","Set price",IF(F8<D8,"LOSS",IF(F8=D8,"Break-even","OK"))) -> Set price | J8: =IF(G8="","",G8*100) | K8: =MIN(B8,CEILING(D8*(1+Settings!$B$4),1)) -> 500
A9: MTN | B9: 1000 | C9: =Settings!$C$9 -> 0.01 | D9: =B9*(1-C9) -> 990 | E9: =CEILING(D9*(1+Settings!$B$5),1) -> 1000 | G9: =IF(F9="","",F9-D9) | H9: =IF(OR(F9="",F9=0),"",G9/F9) | I9: =IF(F9="","Set price",IF(F9<D9,"LOSS",IF(F9=D9,"Break-even","OK"))) -> Set price | J9: =IF(G9="","",G9*100) | K9: =MIN(B9,CEILING(D9*(1+Settings!$B$4),1)) -> 1000
A10: Glo | B10: 100 | C10: =Settings!$C$10 -> 0.02 | D10: =B10*(1-C10) -> 98 | E10: =CEILING(D10*(1+Settings!$B$5),1) -> 99 | G10: =IF(F10="","",F10-D10) | H10: =IF(OR(F10="",F10=0),"",G10/F10) | I10: =IF(F10="","Set price",IF(F10<D10,"LOSS",IF(F10=D10,"Break-even","OK"))) -> Set price | J10: =IF(G10="","",G10*100) | K10: =MIN(B10,CEILING(D10*(1+Settings!$B$4),1)) -> 100
A11: Glo | B11: 200 | C11: =Settings!$C$10 -> 0.02 | D11: =B11*(1-C11) -> 196 | E11: =CEILING(D11*(1+Settings!$B$5),1) -> 198 | G11: =IF(F11="","",F11-D11) | H11: =IF(OR(F11="",F11=0),"",G11/F11) | I11: =IF(F11="","Set price",IF(F11<D11,"LOSS",IF(F11=D11,"Break-even","OK"))) -> Set price | J11: =IF(G11="","",G11*100) | K11: =MIN(B11,CEILING(D11*(1+Settings!$B$4),1)) -> 200
A12: Glo | B12: 300 | C12: =Settings!$C$10 -> 0.02 | D12: =B12*(1-C12) -> 294 | E12: =CEILING(D12*(1+Settings!$B$5),1) -> 297 | G12: =IF(F12="","",F12-D12) | H12: =IF(OR(F12="",F12=0),"",G12/F12) | I12: =IF(F12="","Set price",IF(F12<D12,"LOSS",IF(F12=D12,"Break-even","OK"))) -> Set price | J12: =IF(G12="","",G12*100) | K12: =MIN(B12,CEILING(D12*(1+Settings!$B$4),1)) -> 300
A13: Glo | B13: 500 | C13: =Settings!$C$10 -> 0.02 | D13: =B13*(1-C13) -> 490 | E13: =CEILING(D13*(1+Settings!$B$5),1) -> 495 | G13: =IF(F13="","",F13-D13) | H13: =IF(OR(F13="",F13=0),"",G13/F13) | I13: =IF(F13="","Set price",IF(F13<D13,"LOSS",IF(F13=D13,"Break-even","OK"))) -> Set price | J13: =IF(G13="","",G13*100) | K13: =MIN(B13,CEILING(D13*(1+Settings!$B$4),1)) -> 500
A14: Glo | B14: 1000 | C14: =Settings!$C$10 -> 0.02 | D14: =B14*(1-C14) -> 980 | E14: =CEILING(D14*(1+Settings!$B$5),1) -> 990 | G14: =IF(F14="","",F14-D14) | H14: =IF(OR(F14="",F14=0),"",G14/F14) | I14: =IF(F14="","Set price",IF(F14<D14,"LOSS",IF(F14=D14,"Break-even","OK"))) -> Set price | J14: =IF(G14="","",G14*100) | K14: =MIN(B14,CEILING(D14*(1+Settings!$B$4),1)) -> 1000
A15: Airtel | B15: 100 | C15: =Settings!$C$11 -> 0.02 | D15: =B15*(1-C15) -> 98 | E15: =CEILING(D15*(1+Settings!$B$5),1) -> 99 | G15: =IF(F15="","",F15-D15) | H15: =IF(OR(F15="",F15=0),"",G15/F15) | I15: =IF(F15="","Set price",IF(F15<D15,"LOSS",IF(F15=D15,"Break-even","OK"))) -> Set price | J15: =IF(G15="","",G15*100) | K15: =MIN(B15,CEILING(D15*(1+Settings!$B$4),1)) -> 100
A16: Airtel | B16: 200 | C16: =Settings!$C$11 -> 0.02 | D16: =B16*(1-C16) -> 196 | E16: =CEILING(D16*(1+Settings!$B$5),1) -> 198 | G16: =IF(F16="","",F16-D16) | H16: =IF(OR(F16="",F16=0),"",G16/F16) | I16: =IF(F16="","Set price",IF(F16<D16,"LOSS",IF(F16=D16,"Break-even","OK"))) -> Set price | J16: =IF(G16="","",G16*100) | K16: =MIN(B16,CEILING(D16*(1+Settings!$B$4),1)) -> 200
A17: Airtel | B17: 300 | C17: =Settings!$C$11 -> 0.02 | D17: =B17*(1-C17) -> 294 | E17: =CEILING(D17*(1+Settings!$B$5),1) -> 297 | G17: =IF(F17="","",F17-D17) | H17: =IF(OR(F17="",F17=0),"",G17/F17) | I17: =IF(F17="","Set price",IF(F17<D17,"LOSS",IF(F17=D17,"Break-even","OK"))) -> Set price | J17: =IF(G17="","",G17*100) | K17: =MIN(B17,CEILING(D17*(1+Settings!$B$4),1)) -> 300
A18: Airtel | B18: 500 | C18: =Settings!$C$11 -> 0.02 | D18: =B18*(1-C18) -> 490 | E18: =CEILING(D18*(1+Settings!$B$5),1) -> 495 | G18: =IF(F18="","",F18-D18) | H18: =IF(OR(F18="",F18=0),"",G18/F18) | I18: =IF(F18="","Set price",IF(F18<D18,"LOSS",IF(F18=D18,"Break-even","OK"))) -> Set price | J18: =IF(G18="","",G18*100) | K18: =MIN(B18,CEILING(D18*(1+Settings!$B$4),1)) -> 500
A19: Airtel | B19: 1000 | C19: =Settings!$C$11 -> 0.02 | D19: =B19*(1-C19) -> 980 | E19: =CEILING(D19*(1+Settings!$B$5),1) -> 990 | G19: =IF(F19="","",F19-D19) | H19: =IF(OR(F19="",F19=0),"",G19/F19) | I19: =IF(F19="","Set price",IF(F19<D19,"LOSS",IF(F19=D19,"Break-even","OK"))) -> Set price | J19: =IF(G19="","",G19*100) | K19: =MIN(B19,CEILING(D19*(1+Settings!$B$4),1)) -> 1000
A20: 9mobile | B20: 100 | C20: =Settings!$C$12 -> 0.05 | D20: =B20*(1-C20) -> 95 | E20: =CEILING(D20*(1+Settings!$B$5),1) -> 96 | G20: =IF(F20="","",F20-D20) | H20: =IF(OR(F20="",F20=0),"",G20/F20) | I20: =IF(F20="","Set price",IF(F20<D20,"LOSS",IF(F20=D20,"Break-even","OK"))) -> Set price | J20: =IF(G20="","",G20*100) | K20: =MIN(B20,CEILING(D20*(1+Settings!$B$4),1)) -> 100
A21: 9mobile | B21: 200 | C21: =Settings!$C$12 -> 0.05 | D21: =B21*(1-C21) -> 190 | E21: =CEILING(D21*(1+Settings!$B$5),1) -> 192 | G21: =IF(F21="","",F21-D21) | H21: =IF(OR(F21="",F21=0),"",G21/F21) | I21: =IF(F21="","Set price",IF(F21<D21,"LOSS",IF(F21=D21,"Break-even","OK"))) -> Set price | J21: =IF(G21="","",G21*100) | K21: =MIN(B21,CEILING(D21*(1+Settings!$B$4),1)) -> 200
A22: 9mobile | B22: 300 | C22: =Settings!$C$12 -> 0.05 | D22: =B22*(1-C22) -> 285 | E22: =CEILING(D22*(1+Settings!$B$5),1) -> 288 | G22: =IF(F22="","",F22-D22) | H22: =IF(OR(F22="",F22=0),"",G22/F22) | I22: =IF(F22="","Set price",IF(F22<D22,"LOSS",IF(F22=D22,"Break-even","OK"))) -> Set price | J22: =IF(G22="","",G22*100) | K22: =MIN(B22,CEILING(D22*(1+Settings!$B$4),1)) -> 300
A23: 9mobile | B23: 500 | C23: =Settings!$C$12 -> 0.05 | D23: =B23*(1-C23) -> 475 | E23: =CEILING(D23*(1+Settings!$B$5),1) -> 480 | G23: =IF(F23="","",F23-D23) | H23: =IF(OR(F23="",F23=0),"",G23/F23) | I23: =IF(F23="","Set price",IF(F23<D23,"LOSS",IF(F23=D23,"Break-even","OK"))) -> Set price | J23: =IF(G23="","",G23*100) | K23: =MIN(B23,CEILING(D23*(1+Settings!$B$4),1)) -> 499
A24: 9mobile | B24: 1000 | C24: =Settings!$C$12 -> 0.05 | D24: =B24*(1-C24) -> 950 | E24: =CEILING(D24*(1+Settings!$B$5),1) -> 960 | G24: =IF(F24="","",F24-D24) | H24: =IF(OR(F24="",F24=0),"",G24/F24) | I24: =IF(F24="","Set price",IF(F24<D24,"LOSS",IF(F24=D24,"Break-even","OK"))) -> Set price | J24: =IF(G24="","",G24*100) | K24: =MIN(B24,CEILING(D24*(1+Settings!$B$4),1)) -> 998
A26: Discounts are linked from 'Settings' (live ClubKonnect EPIN discounts). Current KudiTrack price = cost + Enterprise fee, rounded up to the next naira, as in BillPayments.jsx.
